LICENSE
MANIFEST.in
README.md
requirements.txt
setup.py
travel/__init__.py
travel/__main__.py
travel.egg-info/PKG-INFO
travel.egg-info/SOURCES.txt
travel.egg-info/dependency_links.txt
travel.egg-info/entry_points.txt
travel.egg-info/requires.txt
travel.egg-info/top_level.txt
travel/cli/__init__.py
travel/cli/adder.py
travel/cli/base.py
travel/cli/cleaner.py
travel/cli/configurer.py
travel/cli/packer.py
travel/cli/planner.py
travel/cli/setupper.py
travel/cli/takeoffer.py
travel/cli/console/__init__.py
travel/cli/console/output.py
travel/cli/utils/__init__.py
travel/cli/utils/package.py
travel/config/__init__.py
travel/config/bag.py
travel/config/project.py
travel/config/reader.py
travel/config/environment/__init__.py
travel/config/environment/configuration.py
travel/config/environment/python.py
travel/config/sanitizers/__init__.py
travel/config/sanitizers/asserter.py
travel/config/sanitizers/name_sanitizer.py
travel/config/sanitizers/pip_sanitizer.py
travel/config/sanitizers/python_sanitizer.py
travel/config/subconfigs/__init__.py
travel/config/subconfigs/pip.py
travel/config/subconfigs/scopes.py
travel/custom/__init__.py
travel/custom/scopes/__init__.py
travel/custom/scopes/scoped_venvs.py
travel/custom/tasks/__init__.py
travel/custom/tasks/performer.py
travel/custom/tasks/task.py
travel/tools/__init__.py
travel/tools/base_venv.py
travel/tools/executable.py
travel/tools/pip.py
travel/tools/python.py
travel/tools/shell.py
travel/tools/venv.py
travel/tools/outputs/__init__.py
travel/tools/outputs/latest_updates.py