Metadata-Version: 2.1
Name: travel
Version: 0.8.1
Summary: A software manager for easy development and distribution of Python code
Home-page: https://github.com/travel-tools/travel
Author: Federico Pugliese
Author-email: federico.pugliese.wr@gmail.com
License: Apache Software License, Version 2.0
Platform: UNKNOWN
Classifier: License :: OSI Approved :: Apache Software License
Classifier: Development Status :: 4 - Beta
Classifier: Intended Audience :: Developers
Classifier: Programming Language :: Python :: 3
Classifier: Programming Language :: Python :: 3.7
Classifier: Programming Language :: Python :: 3.8
Classifier: Programming Language :: Python :: 3.9
Requires-Python: >=3.7
